veh_sim/__init__.py
veh_sim/environment.py
veh_sim/globals.py
veh_sim/host_vehicle.py
veh_sim/simulation_cfg.json
veh_sim/simulator.py
veh_sim/traffic.py
veh_sim/traffic_router.py
veh_sim/utils.py
veh_sim/vehicle.py
veh_sim/images/bike_0.png
veh_sim/images/bike_1.png
veh_sim/images/bike_2.png
veh_sim/images/bike_3.png
veh_sim/images/bike_4.png
veh_sim/images/bike_5.png
veh_sim/images/car_0.png
veh_sim/images/car_1.png
veh_sim/images/car_10.png
veh_sim/images/car_11.png
veh_sim/images/car_12.png
veh_sim/images/car_2.png
veh_sim/images/car_3.png
veh_sim/images/car_4.png
veh_sim/images/car_5.png
veh_sim/images/car_6.png
veh_sim/images/car_7.png
veh_sim/images/check.png
veh_sim/images/host_0.png
veh_sim/images/host_1.png
veh_sim/images/host_2.png
veh_sim/images/host_3.png
veh_sim/images/house_0.png
veh_sim/images/house_1.png
veh_sim/images/house_2.png
veh_sim/images/house_3.png
veh_sim/images/motor_0.png
veh_sim/images/motor_1.png
veh_sim/images/motor_2.png
veh_sim/images/motor_3.png
veh_sim/images/ped_0.png
veh_sim/images/ped_1.png
veh_sim/images/ped_2.png
veh_sim/images/ped_3.png
veh_sim/images/ped_3_org.png
veh_sim/images/step_1.png
veh_sim/images/step_2.png
veh_sim/images/step_3.png
veh_sim/images/step_4.png
veh_sim/images/step_5.png
veh_sim/images/step_6.png
veh_sim/images/step_7.png
veh_sim/images/tree_0.png
veh_sim/images/tree_1.png
veh_sim/images/tree_2.png
veh_sim/images/tree_3.png
veh_sim/images/x.png
veh_sim-0.7.0.dist-info/METADATA
veh_sim-0.7.0.dist-info/WHEEL
veh_sim-0.7.0.dist-info/top_level.txt
veh_sim-0.7.0.dist-info/RECORD
