Metadata-Version: 2.1
Name: veh-sim
Version: 0.7.0
Summary: A short description of your package
Home-page: https://github.com/your_username/your_package_name
Author: Richard Hamilton
Author-email: r.hamilton@mathstronauts.ca
Classifier: Development Status :: 3 - Alpha
Classifier: Intended Audience :: Developers
Classifier: License :: OSI Approved :: MIT License
Classifier: Programming Language :: Python :: 3
Classifier: Programming Language :: Python :: 3.6
Classifier: Programming Language :: Python :: 3.7
Requires-Dist: pygame
Requires-Dist: easydict
Provides-Extra: dev
Requires-Dist: black >=23.1a1 ; extra == 'dev'
Requires-Dist: flake8 >=3.8.4 ; extra == 'dev'
Requires-Dist: pytest >=6.2.5 ; extra == 'dev'
Requires-Dist: pytest-cov >=2.11.1 ; extra == 'dev'
Requires-Dist: isort >=5.7.0 ; extra == 'dev'
Requires-Dist: pre-commit >=2.9.3 ; extra == 'dev'
Requires-Dist: ipython >=8.8.0 ; extra == 'dev'
Requires-Dist: ipykernel >=6.20.2 ; extra == 'dev'
Requires-Dist: ipywidgets >=7.6.3 ; extra == 'dev'
Requires-Dist: build ; extra == 'dev'
Requires-Dist: twine ; extra == 'dev'
